SecureCrypt/__init__.py
SecureCrypt-1.0.2.dist-info/LICENSE
SecureCrypt-1.0.2.dist-info/METADATA
SecureCrypt-1.0.2.dist-info/WHEEL
SecureCrypt-1.0.2.dist-info/top_level.txt
SecureCrypt-1.0.2.dist-info/RECORD
